[
  {
    "quote": "The best way to get started is to quit talking and begin doing.",
    "author": "Walt Disney",
    "date": "1950-01-01"
  },
  {
    "quote": "Don't let yesterday take up too much of today.",
    "author": "Will Rogers",
    "date": "1935-05-15"
  },
  {
    "quote": "It’s not whether you get knocked down, it’s whether you get up.",
    "author": "Vince Lombardi",
    "date": "1962-11-10"
  },
  {
    "quote": "If you are working on something exciting, it will keep you motivated.",
    "author": "Steve Jobs",
    "date": "2005-06-12"
  },
  {
    "quote": "Success is not in what you have, but who you are.",
    "author": "Bo Bennett",
    "date": "2002-03-19"
  },
  {
    "quote": "Creativity is intelligence having fun.",
    "author": "Albert Einstein",
    "date": "1929-04-30"
  },
  {
    "quote": "Do what you can with all you have, wherever you are.",
    "author": "Theodore Roosevelt",
    "date": "1901-09-14"
  },
  {
    "quote": "You are never too old to set another goal or to dream a new dream.",
    "author": "C.S. Lewis",
    "date": "1945-08-09"
  },
  {
    "quote": "Reading is to the mind, as exercise is to the body.",
    "author": "Brian Tracy",
    "date": "1998-07-22"
  },
  {
    "quote": "Setting goals is the first step in turning the invisible into the visible.",
    "author": "Tony Robbins",
    "date": "2001-12-01"
  },
  {
    "quote": "Your time is limited, so don’t waste it living someone else’s life.",
    "author": "Steve Jobs",
    "date": "2005-06-12"
  },
  {
    "quote": "Success usually comes to those who are too busy to be looking for it.",
    "author": "Henry David Thoreau",
    "date": "1854-09-01"
  },
  {
    "quote": "Hard work beats talent when talent doesn’t work hard.",
    "author": "Tim Notke",
    "date": "2010-10-10"
  },
  {
    "quote": "Don’t watch the clock; do what it does. Keep going.",
    "author": "Sam Levenson",
    "date": "1956-06-03"
  },
  {
    "quote": "Great things are done by a series of small things brought together.",
    "author": "Vincent Van Gogh",
    "date": "1889-03-27"
  },
  {
    "quote": "Success is not final, failure is not fatal: It is the courage to continue that counts.",
    "author": "Winston Churchill",
    "date": "1941-10-29"
  },
  {
    "quote": "Dream big and dare to fail.",
    "author": "Norman Vaughan",
    "date": "1960-05-05"
  },
  {
    "quote": "Don’t be pushed by your problems. Be led by your dreams.",
    "author": "Ralph Waldo Emerson",
    "date": "1860-01-12"
  },
  {
    "quote": "Turn your wounds into wisdom.",
    "author": "Oprah Winfrey",
    "date": "1995-09-09"
  },
  {
    "quote": "The only place where success comes before work is in the dictionary.",
    "author": "Vidal Sassoon",
    "date": "1975-04-17"
  },
  {
    "quote": "You miss 100% of the shots you don’t take.",
    "author": "Wayne Gretzky",
    "date": "1983-03-05"
  },
  {
    "quote": "Only those who dare to fail greatly can ever achieve greatly.",
    "author": "Robert F. Kennedy",
    "date": "1966-06-06"
  },
  {
    "quote": "Action is the foundational key to all success.",
    "author": "Pablo Picasso",
    "date": "1930-07-01"
  },
  {
    "quote": "What you get by achieving your goals is not as important as what you become by achieving your goals.",
    "author": "Zig Ziglar",
    "date": "1982-02-20"
  },
  {
    "quote": "Whether you think you can or you think you can’t, you’re right.",
    "author": "Henry Ford",
    "date": "1923-08-01"
  },
  {
    "quote": "Security is mostly a superstition. Life is either a daring adventure or nothing.",
    "author": "Helen Keller",
    "date": "1903-10-10"
  },
  {
    "quote": "Everything you’ve ever wanted is on the other side of fear.",
    "author": "George Addair",
    "date": "1958-11-11"
  },
  {
    "quote": "If you want to achieve greatness stop asking for permission.",
    "author": "Anonymous",
    "date": "2013-03-21"
  },
  {
    "quote": "Opportunities don’t happen. You create them.",
    "author": "Chris Grosser",
    "date": "2011-06-30"
  },
  {
    "quote": "Try not to become a man of success. Rather become a man of value.",
    "author": "Albert Einstein",
    "date": "1947-04-02"
  }
]
